Metadata-Version: 1.0
Name: pycriaenvio
Version: 0.1
Summary: Integração da API Criaenvio com python
Home-page: https://github.com/peixoto3/python-criaenvio
Author: Guilherme Peixoto
Author-email: gpeixoto3@gmail.com
License: MIT
Platform: UNKNOWN
